bglib/__init__.py
bglib/remover.py
bg_remove-0.2.0.dist-info/METADATA
bg_remove-0.2.0.dist-info/WHEEL
bg_remove-0.2.0.dist-info/top_level.txt
bg_remove-0.2.0.dist-info/RECORD
